wikidb/__about__.py
wikidb/__init__.py
wikidb-0.0.1.dist-info/METADATA
wikidb-0.0.1.dist-info/WHEEL
wikidb-0.0.1.dist-info/licenses/LICENSE.txt
wikidb-0.0.1.dist-info/RECORD
